{"cameraMode":{"drawMode":2,"name":"Shaded Wireframe","section":"Shading Mode"},"sceneLighting":true,"audioPlay":false,"sceneViewState":{"m_AlwaysRefresh":false,"showFog":true,"showSkybox":true,"showFlares":true,"showImageEffects":true,"showParticleSystems":true,"showVisualEffectGraphs":true,"m_FxEnabled":true},"in2DMode":false,"pivot":{"x":-1.495432734489441,"y":0.19919069111347199,"z":2.4201149940490724},"rotation":{"x":-0.15109503269195558,"y":0.6011165976524353,"z":-0.1170477643609047,"w":-0.7759754061698914},"size":1.0586270093917847,"orthographic":false}